{
	"editor": {
		"allAngles": false,
		"entityTextureMode": true
	},
	"textureWidth": 16,
	"textureHeight": 24,
	"textureSizes": {
		"plant2a": [64,32],
		"plant2b": [64,32],
		"plant2astem": [64,32],
		"plant2bstem": [64,32]
	},
	"textures": {
		"digitalis-purpurea": "digitalis-purpurea"
	},
	"elements": [
		{
			"name": "Plant 2a",
			"from": [ 4.0, 0.0, 4.0 ],
			"to": [ 14.0, 32.0, 4.0 ],
			"shade": false,
			"renderPass": 2,
			"autoUnwrap": false,
			"uv": [ 11.62, 2.0 ],
			"rotationOrigin": [ 12.0, 0.0, 7.0 ],
			"rotationY": 45.0,
			"faces": {
				"north": { "texture": "#null", "uv": [ 12.0, 2.0, 22.0, 34.0 ], "windMode": [-1,-1,-1,-1], "windData": [0,2,2,0], "enabled": false },
				"east": { "texture": "#digitalis-purpurea", "uv": [ 10.92, -1.12, 13.0, 24.15 ], "autoUv": false, "windMode": [-1,-1,-1,-1], "windData": [0,2,2,0] },
				"south": { "texture": "#plant2a", "uv": [ 12.0, 2.0, 22.0, 34.0 ], "windMode": [0,0,2,2], "windData": [0,0,2,2] },
				"west": { "texture": "#null", "uv": [ 12.0, 2.0, 12.5, 34.0 ], "windMode": [-1,-1,-1,-1], "windData": [0,0,2,2], "enabled": false },
				"up": { "texture": "#null", "uv": [ 12.5, 2.0, 22.5, 2.5 ], "rotation": 180, "windMode": [-1,-1,-1,-1], "windData": [2,2,2,2], "enabled": false },
				"down": { "texture": "#null", "uv": [ 12.0, 34.0, 22.0, 34.5 ], "enabled": false }
			},
			"children": [
				{
					"name": "Plant 2b",
					"from": [ 5.0, 0.0, -5.0 ],
					"to": [ 5.0, 31.8, 6.0 ],
					"shade": false,
					"renderPass": 2,
					"unwrapMode": 1,
					"autoUnwrap": false,
					"uv": [ 7.62, 0.0 ],
					"rotationOrigin": [ 5.0, 0.0, 0.0 ],
					"faces": {
						"north": { "texture": "#null", "uv": [ 19.0, 0.0, 19.5, 31.5 ], "enabled": false },
						"east": { "texture": "#digitalis-purpurea", "uv": [ 11.02, -1.0, 13.02, 24.5 ], "autoUv": false, "windMode": [0,2,2,0], "windData": [0,1,1,0] },
						"south": { "texture": "#null", "uv": [ 19.0, 0.0, 19.5, 31.5 ], "enabled": false },
						"west": { "texture": "#null", "uv": [ 19.0, 0.0, 30.0, 31.5 ], "enabled": false },
						"up": { "texture": "#null", "uv": [ 19.0, 0.0, 19.5, 11.0 ], "rotation": 180, "enabled": false },
						"down": { "texture": "#null", "uv": [ 19.0, 31.5, 19.5, 42.5 ], "enabled": false }
					}
				}
			]
		},
		{
			"name": "Plant 2a stem",
			"from": [ 4.0, 0.0, 4.0 ],
			"to": [ 14.0, 24.0, 4.0 ],
			"shade": false,
			"climateColorMap": "climatePlantTint",
			"seasonColorMap": "seasonalFoliage",
			"renderPass": 2,
			"autoUnwrap": false,
			"uv": [ 10.0, 6.5 ],
			"rotationOrigin": [ 12.0, 0.0, 7.0 ],
			"rotationY": 45.0,
			"faces": {
				"north": { "texture": "#null", "uv": [ 0.0, 0.0, 10.0, 24.0 ], "enabled": false },
				"east": { "texture": "#null", "uv": [ 0.0, 0.0, 0.5, 24.0 ], "enabled": false },
				"south": { "texture": "#digitalis-purpurea", "uv": [ 9.375, 5.25, 10.375, 24.255 ], "autoUv": false, "windMode": [0,0,2,2], "windData": [0,0,1,1] },
				"west": { "texture": "#null", "uv": [ 0.0, 0.0, 0.5, 24.0 ], "enabled": false },
				"up": { "texture": "#null", "uv": [ 0.0, 0.0, 10.0, 0.5 ], "enabled": false },
				"down": { "texture": "#null", "uv": [ 0.0, 0.0, 10.0, 0.5 ], "enabled": false }
			},
			"children": [
				{
					"name": "Plant 2b stem",
					"from": [ 5.0, 0.0, -5.0 ],
					"to": [ 5.0, 24.0, 5.0 ],
					"shade": false,
					"climateColorMap": "climatePlantTint",
					"seasonColorMap": "seasonalFoliage",
					"renderPass": 2,
					"autoUnwrap": false,
					"uv": [ 5.5, 0.5 ],
					"rotationOrigin": [ 5.0, 0.0, 0.0 ],
					"faces": {
						"north": { "texture": "#null", "uv": [ 10.5, 0.0, 11.0, 24.0 ], "windMode": [-1,-1,-1,-1], "windData": [0,1,1,0], "enabled": false },
						"east": { "texture": "#digitalis-purpurea", "uv": [ 7.0, 4.875, 8.0, 23.87 ], "autoUv": false, "windMode": [0,2,2,0], "windData": [0,1,1,0] },
						"south": { "texture": "#null", "uv": [ 10.5, 0.0, 11.0, 24.0 ], "windMode": [-1,-1,-1,-1], "windData": [0,0,1,1], "enabled": false },
						"west": { "texture": "#null", "uv": [ 10.5, 0.0, 20.5, 24.0 ], "enabled": false },
						"up": { "texture": "#null", "uv": [ 10.5, 0.0, 11.0, 10.0 ], "rotation": 180, "windMode": [-1,-1,-1,-1], "windData": [1,1,1,1], "enabled": false },
						"down": { "texture": "#null", "uv": [ 10.5, 24.0, 11.0, 34.0 ], "enabled": false }
					}
				}
			]
		}
	]}